vai_jobspec_tools.py
vai_jobspec_tools-2.1.0.dist-info/WHEEL
vai_jobspec_tools-2.1.0.dist-info/METADATA
vai_jobspec_tools-2.1.0.dist-info/RECORD
