Metadata-Version: 2.1
Name: vai-jobspec-tools
Version: 2.1.0
Summary: Utilities for VoxelAI jobspec containers
Home-page: https://github.com/voxelai/vai-jobspec-tools
Author: Andrew Ross
Author-email: andrew.ross.mail@gmail.com
Requires-Python: >=3.7,<4.0
Classifier: Programming Language :: Python :: 3
Classifier: Programming Language :: Python :: 3.7
Classifier: Programming Language :: Python :: 3.8
Classifier: Programming Language :: Python :: 3.9
Classifier: Programming Language :: Python :: 3.10
Classifier: Programming Language :: Python :: 3.11
Project-URL: Documentation, https://github.com/voxelai/vai-jobspec-tools
Project-URL: Repository, https://github.com/voxelai/vai-jobspec-tools
